simplefib.py
_fib.cpython-310-x86_64-linux-gnu.so
simplefib-0.5.dist-info/METADATA
simplefib-0.5.dist-info/top_level.txt
simplefib-0.5.dist-info/RECORD
simplefib-0.5.dist-info/WHEEL
simplefib-0.5.dist-info/LICENSE
